{"chunk_definitions":[{"row":15,"row_count":1,"visible":true,"expansion_state":0,"options":{"engine":"r","label":"setup","include":false},"document_id":"6D896DD0","chunk_id":"csetup_chunk","chunk_label":"setup"},{"row":44,"row_count":1,"visible":true,"expansion_state":0,"options":{"engine":"r","label":"unnamed-chunk-292"},"document_id":"75229BEC","chunk_id":"cachvuvi98dvc","chunk_label":"unnamed-chunk-1"},{"row":61,"row_count":1,"visible":true,"expansion_state":0,"options":{"engine":"r","class.source":"fold-show","label":"unnamed-chunk-293"},"document_id":"6D896DD0","chunk_id":"csk09sloxcuuw","chunk_label":"unnamed-chunk-2"},{"row":69,"row_count":1,"visible":true,"expansion_state":0,"options":{"engine":"r","class.source":"fold-show","label":"unnamed-chunk-294"},"document_id":"6D896DD0","chunk_id":"cck7lptgs55jj","chunk_label":"unnamed-chunk-3"},{"row":87,"row_count":1,"visible":true,"expansion_state":0,"options":{"engine":"r","class.source":"fold-show","label":"unnamed-chunk-296"},"document_id":"7D9984DF","chunk_id":"cw1lbvdz5di89","chunk_label":"unnamed-chunk-4"},{"row":97,"row_count":1,"visible":true,"expansion_state":0,"options":{"engine":"r","class.source":"fold-show","label":"unnamed-chunk-298"},"document_id":"7D9984DF","chunk_id":"cuksyk6ueb7m2","chunk_label":"unnamed-chunk-5"},{"row":113,"row_count":1,"visible":true,"expansion_state":0,"options":{"engine":"r","label":"unnamed-chunk-302"},"document_id":"7D9984DF","chunk_id":"ccyix0cj3uiw5","chunk_label":"unnamed-chunk-6"},{"row":126,"row_count":1,"visible":true,"expansion_state":0,"options":{"engine":"r","label":"unnamed-chunk-306"},"document_id":"7D9984DF","chunk_id":"cpd4n0ejs15tx","chunk_label":"unnamed-chunk-7"},{"row":136,"row_count":1,"visible":true,"expansion_state":0,"options":{"engine":"r","label":"unnamed-chunk-313"},"document_id":"7D9984DF","chunk_id":"c7vy4b3u79ltl","chunk_label":"unnamed-chunk-8"},{"row":142,"row_count":1,"visible":true,"expansion_state":0,"options":{"engine":"r","label":"unnamed-chunk-308"},"document_id":"7D9984DF","chunk_id":"cor94y40g9fk6","chunk_label":"unnamed-chunk-9"},{"row":149,"row_count":1,"visible":true,"expansion_state":0,"options":{"engine":"r","label":"unnamed-chunk-309"},"document_id":"7D9984DF","chunk_id":"czylnic4b8bit","chunk_label":"unnamed-chunk-10"},{"row":157,"row_count":1,"visible":true,"expansion_state":0,"options":{"engine":"r","label":"unnamed-chunk-310"},"document_id":"7D9984DF","chunk_id":"ch2q1asjer2zj","chunk_label":"unnamed-chunk-11"},{"row":166,"row_count":1,"visible":true,"expansion_state":0,"options":{"engine":"r","label":"unnamed-chunk-330"},"document_id":"7D9984DF","chunk_id":"cmkqpcz1csngp","chunk_label":"unnamed-chunk-12"},{"row":174,"row_count":1,"visible":true,"expansion_state":0,"options":{"engine":"r","label":"unnamed-chunk-327"},"document_id":"7D9984DF","chunk_id":"cxgamtc4rr58l","chunk_label":"unnamed-chunk-13"},{"row":183,"row_count":1,"visible":true,"expansion_state":0,"options":{"engine":"r","label":"unnamed-chunk-328"},"document_id":"7D9984DF","chunk_id":"ckem2xpk2q8an","chunk_label":"unnamed-chunk-14"},{"row":192,"row_count":1,"visible":true,"expansion_state":0,"options":{"engine":"r","label":"unnamed-chunk-332"},"document_id":"7D9984DF","chunk_id":"cznhk6yjfehxp","chunk_label":"unnamed-chunk-15"},{"row":201,"row_count":1,"visible":true,"expansion_state":0,"options":{"engine":"r","label":"unnamed-chunk-333"},"document_id":"7D9984DF","chunk_id":"ctvyrvunplms1","chunk_label":"unnamed-chunk-16"},{"row":214,"row_count":1,"visible":true,"expansion_state":0,"options":{"engine":"r","label":"unnamed-chunk-352"},"document_id":"7D9984DF","chunk_id":"cj8pym7emmmyt","chunk_label":"unnamed-chunk-17"},{"row":223,"row_count":1,"visible":true,"expansion_state":0,"options":{"engine":"r","label":"unnamed-chunk-353"},"document_id":"7D9984DF","chunk_id":"cdd8sli9c7r3o","chunk_label":"unnamed-chunk-18"},{"row":233,"row_count":1,"visible":true,"expansion_state":0,"options":{"engine":"r","label":"unnamed-chunk-336"},"document_id":"7D9984DF","chunk_id":"ctlueqjzrpg2g","chunk_label":"unnamed-chunk-19"},{"row":241,"row_count":1,"visible":true,"expansion_state":0,"options":{"engine":"r","label":"unnamed-chunk-337"},"document_id":"7D9984DF","chunk_id":"c6kk0aimbhzky","chunk_label":"unnamed-chunk-20"},{"row":250,"row_count":1,"visible":true,"expansion_state":0,"options":{"engine":"r","label":"unnamed-chunk-338"},"document_id":"7D9984DF","chunk_id":"cx8jk5c4le8h0","chunk_label":"unnamed-chunk-21"},{"row":259,"row_count":1,"visible":true,"expansion_state":0,"options":{"engine":"r","label":"unnamed-chunk-339"},"document_id":"7D9984DF","chunk_id":"cel1ylfggcc42","chunk_label":"unnamed-chunk-22"},{"row":266,"row_count":1,"visible":true,"expansion_state":0,"options":{"engine":"r","label":"unnamed-chunk-340"},"document_id":"7D9984DF","chunk_id":"cqusp59ch5kvu","chunk_label":"unnamed-chunk-23"},{"row":276,"row_count":1,"visible":true,"expansion_state":0,"options":{"engine":"r","label":"unnamed-chunk-354"},"document_id":"7D9984DF","chunk_id":"c5vnya9br51iy","chunk_label":"unnamed-chunk-24"},{"row":286,"row_count":1,"visible":true,"expansion_state":0,"options":{"engine":"r","label":"unnamed-chunk-355"},"document_id":"7D9984DF","chunk_id":"c2nao2txsu0y2","chunk_label":"unnamed-chunk-25"},{"row":295,"row_count":1,"visible":true,"expansion_state":0,"options":{"engine":"r","label":"unnamed-chunk-346"},"document_id":"7D9984DF","chunk_id":"cpssu6htzwx0g","chunk_label":"unnamed-chunk-26"},{"row":306,"row_count":1,"visible":true,"expansion_state":0,"options":{"engine":"r","label":"unnamed-chunk-347"},"document_id":"7D9984DF","chunk_id":"c5troxnpif326","chunk_label":"unnamed-chunk-27"}],"doc_write_time":1675143564,"working_dir":null,"default_chunk_options":{"echo":true,"message":false,"warning":false},"chunk_rendered_width":400}