{"chunk_definitions":[{"row":13,"row_count":1,"visible":true,"expansion_state":0,"options":{"engine":"r","label":"setup","include":false},"document_id":"21C202A9","chunk_id":"csetup_chunk","chunk_label":"setup"},{"row":30,"row_count":1,"visible":true,"expansion_state":0,"options":{"engine":"r","label":"unnamed-chunk-98"},"document_id":"7642AA99","chunk_id":"c8x1ag21lcbgv","chunk_label":"unnamed-chunk-1"},{"row":70,"row_count":1,"visible":true,"expansion_state":0,"options":{"engine":"r","label":"unnamed-chunk-28"},"document_id":"21C202A9","chunk_id":"c4oei3c13epvc","chunk_label":"unnamed-chunk-4"},{"row":93,"row_count":1,"visible":true,"expansion_state":0,"options":{"engine":"r","label":"unnamed-chunk-32"},"document_id":"7642AA99","chunk_id":"c77zs4jjbfgka","chunk_label":"unnamed-chunk-7"},{"row":101,"row_count":1,"visible":true,"expansion_state":0,"options":{"engine":"r","label":"unnamed-chunk-34"},"document_id":"7642AA99","chunk_id":"cmrskzpjsvfuh","chunk_label":"unnamed-chunk-8"},{"row":119,"row_count":1,"visible":true,"expansion_state":0,"options":{"engine":"r","label":"unnamed-chunk-37"},"document_id":"7642AA99","chunk_id":"cm27pztmyyf65","chunk_label":"unnamed-chunk-10"},{"row":128,"row_count":1,"visible":true,"expansion_state":0,"options":{"engine":"r","label":"unnamed-chunk-39"},"document_id":"7642AA99","chunk_id":"clwd85k8mzxww","chunk_label":"unnamed-chunk-11"},{"row":162,"row_count":1,"visible":true,"expansion_state":0,"options":{"engine":"r","label":"unnamed-chunk-45"},"document_id":"7642AA99","chunk_id":"cp44jmobtw2x7","chunk_label":"unnamed-chunk-14"},{"row":184,"row_count":1,"visible":true,"expansion_state":0,"options":{"engine":"r","label":"unnamed-chunk-50"},"document_id":"7642AA99","chunk_id":"cl6jkytz0anm1","chunk_label":"unnamed-chunk-16"},{"row":200,"row_count":1,"visible":true,"expansion_state":0,"options":{"engine":"r","label":"unnamed-chunk-66"},"document_id":"7642AA99","chunk_id":"cpo9dfg9szpk6","chunk_label":"unnamed-chunk-18"},{"row":205,"row_count":1,"visible":true,"expansion_state":0,"options":{"engine":"r","label":"unnamed-chunk-67"},"document_id":"7642AA99","chunk_id":"c1x242xhogjut","chunk_label":"unnamed-chunk-19"},{"row":213,"row_count":1,"visible":true,"expansion_state":0,"options":{"engine":"r","label":"unnamed-chunk-68"},"document_id":"7642AA99","chunk_id":"cajnob2l7firn","chunk_label":"unnamed-chunk-20"},{"row":242,"row_count":1,"visible":true,"expansion_state":0,"options":{"engine":"r","label":"unnamed-chunk-74"},"document_id":"7642AA99","chunk_id":"ch4uiy6ek3pgg","chunk_label":"unnamed-chunk-22"},{"row":271,"row_count":1,"visible":true,"expansion_state":0,"options":{"engine":"r","label":"unnamed-chunk-80"},"document_id":"7642AA99","chunk_id":"cn6wqi2r5mgkd","chunk_label":"unnamed-chunk-25"},{"row":288,"row_count":1,"visible":true,"expansion_state":0,"options":{"engine":"r","label":"unnamed-chunk-84"},"document_id":"7642AA99","chunk_id":"cv4uytk3h4jau","chunk_label":"unnamed-chunk-27"},{"row":295,"row_count":1,"visible":true,"expansion_state":0,"options":{"engine":"r","label":"unnamed-chunk-85"},"document_id":"7642AA99","chunk_id":"cafdoxzfh2pg9","chunk_label":"unnamed-chunk-28"},{"row":304,"row_count":1,"visible":true,"expansion_state":0,"options":{"engine":"r","label":"unnamed-chunk-86"},"document_id":"7642AA99","chunk_id":"cs4kbzqc7liba","chunk_label":"unnamed-chunk-29"},{"row":314,"row_count":1,"visible":true,"expansion_state":0,"options":{"engine":"r","label":"unnamed-chunk-87"},"document_id":"7642AA99","chunk_id":"cnq73gwzp0bvf","chunk_label":"unnamed-chunk-30"},{"row":328,"row_count":1,"visible":true,"expansion_state":0,"options":{"engine":"r","label":"unnamed-chunk-90"},"document_id":"7642AA99","chunk_id":"ctlr1tef9sojz","chunk_label":"unnamed-chunk-32"},{"row":333,"row_count":1,"visible":true,"expansion_state":0,"options":{"engine":"r","label":"unnamed-chunk-92"},"document_id":"7642AA99","chunk_id":"cdn1pdpym4uhx","chunk_label":"unnamed-chunk-33"},{"row":346,"row_count":1,"visible":true,"expansion_state":0,"options":{"engine":"r","label":"unnamed-chunk-93"},"document_id":"7642AA99","chunk_id":"cfr4h10pbyyt9","chunk_label":"unnamed-chunk-34"},{"row":354,"row_count":1,"visible":true,"expansion_state":0,"options":{"engine":"r","label":"unnamed-chunk-94"},"document_id":"7642AA99","chunk_id":"cg1nhooqsgqvl","chunk_label":"unnamed-chunk-35"},{"row":374,"row_count":1,"visible":true,"expansion_state":0,"options":{"engine":"r","label":"unnamed-chunk-99"},"document_id":"7642AA99","chunk_id":"cs6klxdidqptr","chunk_label":"unnamed-chunk-37"}],"doc_write_time":1652687146,"chunk_rendered_width":700}